{
  "name": "memogram",
  "type": "app",
  "title": "Memogram",
  "slogan": "Memos 的 Telegram 机器人集成",
  "description": "Memogram is an easy to use integration service for syncing messages and images from a Telegram bot into your Memos.",
  "license": "Custom properties",
  "variants": {
    "latest": {
      "version": "0.4.2",
      "sha": "ae833095b8006e7bf9636e7ed4517df9943812e9",
      "checkver": {
        "type": "tag",
        "repo": "https://github.com/usememos/telegram-integration"
      }
    }
  }
}